{
  "__comment__": "This file was automatically created by mcresources",
  "type": "minecraft:crafting_shapeless",
  "ingredients": [
    {
      "tag": "forge:gravel"
    },
    {
      "tag": "forge:sand"
    },
    {
      "tag": "forge:gravel"
    },
    {
      "tag": "forge:sand"
    },
    {
      "item": "tfc:powder/lime"
    },
    {
      "tag": "forge:sand"
    },
    {
      "tag": "forge:gravel"
    },
    {
      "tag": "forge:sand"
    },
    {
      "tag": "forge:gravel"
    }
  ],
  "result": {
    "item": "tfc:aggregate",
    "count": 8
  }
}